mlx_knife-2.0.3.dist-info/licenses/LICENSE
mlx_knife-2.0.3.dist-info/licenses/mlxk2/NOTICE
mlxk2/NOTICE
mlxk2/__init__.py
mlxk2/cli.py
mlxk2/context.py
mlxk2/errors.py
mlxk2/logging.py
mlxk2/spec.py
mlxk2/core/__init__.py
mlxk2/core/cache.py
mlxk2/core/model_resolution.py
mlxk2/core/reasoning.py
mlxk2/core/server_base.py
mlxk2/core/runner/__init__.py
mlxk2/core/runner/chat_format.py
mlxk2/core/runner/reasoning_format.py
mlxk2/core/runner/stop_tokens.py
mlxk2/core/runner/token_limits.py
mlxk2/operations/__init__.py
mlxk2/operations/clone.py
mlxk2/operations/common.py
mlxk2/operations/health.py
mlxk2/operations/list.py
mlxk2/operations/pull.py
mlxk2/operations/push.py
mlxk2/operations/rm.py
mlxk2/operations/run.py
mlxk2/operations/serve.py
mlxk2/operations/show.py
mlxk2/output/__init__.py
mlxk2/output/human.py
mlx_knife-2.0.3.dist-info/METADATA
mlx_knife-2.0.3.dist-info/WHEEL
mlx_knife-2.0.3.dist-info/entry_points.txt
mlx_knife-2.0.3.dist-info/top_level.txt
mlx_knife-2.0.3.dist-info/RECORD
