Metadata-Version: 2.4
Name: mlx-knife
Version: 2.0.3
Summary: HuggingFace model management for MLX on Apple Silicon
Author-email: The BROKE team <broke@gmx.eu>
License: Apache-2.0
Project-URL: Homepage, https://github.com/mzau/mlx-knife
Project-URL: Repository, https://github.com/mzau/mlx-knife
Project-URL: Issues, https://github.com/mzau/mlx-knife/issues
Classifier: Development Status :: 5 - Production/Stable
Classifier: Intended Audience :: Developers
Classifier: Topic :: Scientific/Engineering :: Artificial Intelligence
Classifier: Programming Language :: Python :: 3
Classifier: Programming Language :: Python :: 3.9
Classifier: Programming Language :: Python :: 3.10
Classifier: Programming Language :: Python :: 3.11
Classifier: Programming Language :: Python :: 3.12
Classifier: Programming Language :: Python :: 3.13
Classifier: Operating System :: MacOS
Classifier: Environment :: Console
Classifier: License :: OSI Approved :: Apache Software License
Requires-Python: >=3.9
License-File: LICENSE
License-File: mlxk2/NOTICE
Requires-Dist: huggingface-hub<1.0,>=0.34.0
Requires-Dist: requests>=2.32.0
Requires-Dist: mlx-lm>=0.28.3
Requires-Dist: mlx>=0.29.0
Requires-Dist: fastapi>=0.116.0
Requires-Dist: uvicorn>=0.35.0
Requires-Dist: pydantic>=2.11.0
Requires-Dist: httpx>=0.27.0
Provides-Extra: test
Requires-Dist: pytest>=7; extra == "test"
Requires-Dist: jsonschema>=4.20; extra == "test"
Provides-Extra: dev
Requires-Dist: ruff>=0.1.0; extra == "dev"
Requires-Dist: mypy>=1.5.0; extra == "dev"
Dynamic: license-file
